cuda_friendly_vincenty/__init__.py
cuda_friendly_vincenty-0.1.2.dist-info/METADATA
cuda_friendly_vincenty-0.1.2.dist-info/RECORD
cuda_friendly_vincenty-0.1.2.dist-info/WHEEL
cuda_friendly_vincenty-0.1.2.dist-info/top_level.txt
