Metadata-Version: 2.1
Name: cuda-friendly-vincenty
Version: 0.1.2
Summary: Function for geographical distances calculation that can run on GPU using CUDA.
Home-page: https://github.com/felytic/cuda-friendly-vincenty
Author: Serhii Hulko
Author-email: felytic@gmail.com
License: Unlicense
Platform: UNKNOWN
Classifier: Development Status :: 4 - Beta
Classifier: Intended Audience :: Developers
Classifier: License :: Public Domain
Classifier: Operating System :: OS Independent
Classifier: Programming Language :: Python
Classifier: Programming Language :: Python :: 2
Classifier: Programming Language :: Python :: 3
Classifier: Topic :: Scientific/Engineering :: Mathematics
